{
    "Alstahaug": "NO4",
    "Alta": "NO4",
    "Alvdal": "NO1",
    "Alver": "NO5",
    "Andøy": "NO4",
    "Aremark": "NO1",
    "Arendal": "NO2",
    "Asker": "NO1",
    "Askvoll": "NO3",
    "Askøy": "NO5",
    "Aukra": "NO3",
    "Aure": "NO3",
    "Aurland": "NO5",
    "Aurskog-Høland": "NO1",
    "Austevoll": "NO2",
    "Austrheim": "NO5",
    "Averøy": "NO3",
    "Balsfjord": "NO4",
    "Bamble": "NO2",
    "Bardu": "NO4",
    "Beiarn": "NO4",
    "Bergen": "NO5",
    "Berlevåg": "NO4",
    "Bindal (Bogen)": "NO3",
    "Bindal (resten)": "NO4",
    "Birkenes": "NO2",
    "Bjerkreim": "NO2",
    "Bjørnafjorden (vest)": "NO5",
    "Bjørnafjorden (øst)": "NO2",
    "Bodø": "NO4",
    "Bokn": "NO2",
    "Bremanger": "NO3",
    "Brønnøy": "NO4",
    "Bygland": "NO2",
    "Bykle": "NO2",
    "Bærum": "NO1",
    "Bø": "NO4",
    "Bømlo": "NO2",
    "Båtsfjord": "NO4",
    "Dovre": "NO3",
    "Drammen (Svelvik)": "NO2",
    "Drammen (unntatt Svelvik)": "NO1",
    "Drangedal": "NO2",
    "Dyrøy": "NO4",
    "Dønna": "NO4",
    "Eidfjord": "NO5",
    "Eidskog": "NO1",
    "Eidsvoll": "NO1",
    "Eigersund": "NO2",
    "Elverum": "NO1",
    "Enebakk": "NO1",
    "Engerdal": "NO1",
    "Etne": "NO2",
    "Etnedal": "NO1",
    "Evenes": "NO4",
    "Evje og Hornnes": "NO2",
    "Farsund": "NO2",
    "Fauske": "NO4",
    "Fedje": "NO5",
    "Fitjar": "NO2",
    "Fjaler": "NO3",
    "Fjord": "NO3",
    "Flakstad": "NO4",
    "Flatanger": "NO3",
    "Flekkefjord": "NO2",
    "Flesberg": "NO1",
    "Flå": "NO5",
    "Folldal (nordvest for Folldal tettsted)": "NO3",
    "Folldal (resten)": "NO1",
    "Fredrikstad": "NO1",
    "Frogn": "NO1",
    "Froland": "NO2",
    "Frosta": "NO3",
    "Frøya": "NO3",
    "Fyresdal": "NO2",
    "Færder": "NO2",
    "Gamvik": "NO4",
    "Gausdal": "NO1",
    "Gildeskål": "NO4",
    "Giske": "NO3",
    "Gjemnes": "NO3",
    "Gjerdrum": "NO1",
    "Gjerstad": "NO2",
    "Gjesdal": "NO2",
    "Gjøvik": "NO1",
    "Gloppen": "NO3",
    "Gol": "NO5",
    "Gran": "NO1",
    "Grane": "NO4",
    "Gratangen": "NO4",
    "Grimstad": "NO2",
    "Grong (nordøst)": "NO4",
    "Grong (sørvest)": "NO3",
    "Grue": "NO1",
    "Gulen": "NO5",
    "Hadsel": "NO4",
    "Halden": "NO1",
    "Hamar": "NO1",
    "Hamarøy": "NO4",
    "Hammerfest": "NO4",
    "Hareid": "NO3",
    "Harstad": "NO4",
    "Hasvik": "NO4",
    "Hattfjelldal": "NO4",
    "Haugesund": "NO2",
    "Heim": "NO3",
    "Hemnes": "NO4",
    "Hemsedal": "NO5",
    "Herøy (Møre og Romsdal)": "NO3",
    "Herøy (Nordland)": "NO4",
    "Hitra": "NO3",
    "Hjartdal": "NO2",
    "Hjelmeland": "NO2",
    "Hol": "NO5",
    "Hole": "NO1",
    "Holmestrand": "NO2",
    "Holtålen": "NO3",
    "Horten": "NO2",
    "Hurdal": "NO1",
    "Hustadvika": "NO3",
    "Hvaler": "NO1",
    "Hyllestad": "NO3",
    "Hægebostad": "NO2",
    "Høyanger (nordvest)": "NO3",
    "Høyanger (sør og øst)": "NO5",
    "Høylandet": "NO3",
    "Hå": "NO2",
    "Ibestad": "NO4",
    "Inderøy": "NO3",
    "Indre Fosen": "NO3",
    "Indre Østfold": "NO1",
    "Iveland": "NO2",
    "Jevnaker": "NO1",
    "Karasjok": "NO4",
    "Karlsøy": "NO4",
    "Karmøy": "NO2",
    "Kautokeino": "NO4",
    "Kinn": "NO3",
    "Klepp": "NO2",
    "Kongsberg": "NO1",
    "Kongsvinger": "NO1",
    "Kragerø": "NO2",
    "Kristiansand": "NO2",
    "Kristiansund": "NO3",
    "Krødsherad": "NO1",
    "Kvam": "NO5",
    "Kvinesdal": "NO2",
    "Kvinnherad": "NO2",
    "Kviteseid": "NO2",
    "Kvitsøy": "NO2",
    "Kvæfjord": "NO4",
    "Kvænangen": "NO4",
    "Kåfjord": "NO4",
    "Larvik": "NO2",
    "Lavangen": "NO4",
    "Lebesby": "NO4",
    "Leirfjord": "NO4",
    "Leka": "NO3",
    "Lesja": "NO3",
    "Levanger": "NO3",
    "Lier": "NO1",
    "Lierne": "NO4",
    "Lillehammer": "NO1",
    "Lillesand": "NO2",
    "Lillestrøm": "NO1",
    "Lindesnes": "NO2",
    "Lom": "NO3",
    "Loppa": "NO4",
    "Lund": "NO2",
    "Lunner": "NO1",
    "Lurøy": "NO4",
    "Luster": "NO5",
    "Lyngdal": "NO2",
    "Lyngen": "NO4",
    "Lærdal": "NO5",
    "Lødingen": "NO4",
    "Lørenskog": "NO1",
    "Løten": "NO1",
    "Malvik": "NO3",
    "Marker": "NO1",
    "Masfjorden": "NO5",
    "Melhus": "NO3",
    "Meløy": "NO4",
    "Meråker": "NO3",
    "Midt-Telemark": "NO2",
    "Midtre Gauldal": "NO3",
    "Modalen": "NO5",
    "Modum": "NO1",
    "Molde": "NO3",
    "Moskenes": "NO4",
    "Moss": "NO1",
    "Målselv": "NO4",
    "Måsøy": "NO4",
    "Namsos": "NO3",
    "Namsskogan": "NO4",
    "Nannestad": "NO1",
    "Narvik": "NO4",
    "Nes": "NO1",
    "Nesbyen": "NO5",
    "Nesna": "NO4",
    "Nesodden": "NO1",
    "Nesseby": "NO4",
    "Nissedal": "NO2",
    "Nittedal": "NO1",
    "Nome": "NO2",
    "Nord-Aurdal": "NO1",
    "Nord-Fron": "NO1",
    "Nord-Odal": "NO1",
    "Nordkapp": "NO4",
    "Nordre Follo": "NO1",
    "Nordre Land": "NO1",
    "Nordreisa": "NO4",
    "Nore og Uvdal": "NO5",
    "Notodden (Meheia-området)": "NO4",
    "Notodden (resten)": "NO2",
    "Nærøysund": "NO3",
    "Oppdal": "NO3",
    "Orkland": "NO3",
    "Os": "NO1",
    "Osen": "NO3",
    "Oslo": "NO1",
    "Osterøy": "NO5",
    "Overhalla": "NO3",
    "Porsanger": "NO4",
    "Porsgrunn": "NO2",
    "Rakkestad": "NO1",
    "Rana": "NO4",
    "Randaberg": "NO2",
    "Rauma": "NO3",
    "Rendalen": "NO1",
    "Rennebu": "NO3",
    "Rindal": "NO3",
    "Ringebu": "NO1",
    "Ringerike": "NO1",
    "Ringsaker": "NO1",
    "Risør": "NO2",
    "Rollag": "NO1",
    "Rælingen": "NO1",
    "Rødøy": "NO4",
    "Røros": "NO1",
    "Røst": "NO4",
    "Røyrvik": "NO4",
    "Råde": "NO1",
    "Salangen": "NO4",
    "Saltdal": "NO4",
    "Samnanger": "NO5",
    "Sande": "NO3",
    "Sandefjord": "NO2",
    "Sandnes": "NO2",
    "Sarpsborg": "NO1",
    "Sauda": "NO2",
    "Sel (resten)": "NO3",
    "Sel (Sjoa tettsted)": "NO1",
    "Selbu": "NO3",
    "Seljord": "NO2",
    "Senja": "NO4",
    "Sigdal": "NO1",
    "Siljan": "NO2",
    "Sirdal": "NO2",
    "Skaun": "NO3",
    "Skien": "NO2",
    "Skiptvet": "NO1",
    "Skjervøy": "NO4",
    "Skjåk": "NO3",
    "Smøla": "NO3",
    "Snåsa": "NO3",
    "Sogndal": "NO5",
    "Sokndal": "NO2",
    "Sola": "NO2",
    "Solund": "NO3",
    "Sortland": "NO4",
    "Stad": "NO3",
    "Stange": "NO1",
    "Stavanger": "NO2",
    "Steigen": "NO4",
    "Steinkjer": "NO3",
    "Stjørdal": "NO3",
    "Stor-Elvdal": "NO1",
    "Stord": "NO2",
    "Storfjord": "NO4",
    "Strand": "NO2",
    "Stranda": "NO3",
    "Stryn": "NO3",
    "Sula": "NO3",
    "Suldal": "NO2",
    "Sunndal": "NO3",
    "Sunnfjord": "NO3",
    "Surnadal": "NO3",
    "Sveio": "NO2",
    "Sykkylven": "NO3",
    "Sømna": "NO4",
    "Søndre Land": "NO1",
    "Sør-Aurdal": "NO1",
    "Sør-Fron": "NO1",
    "Sør-Odal": "NO1",
    "Sør-Varanger": "NO4",
    "Sørfold": "NO4",
    "Sørreisa": "NO4",
    "Tana": "NO4",
    "Time": "NO2",
    "Tingvoll": "NO3",
    "Tinn": "NO2",
    "Tjeldsund": "NO4",
    "Tokke": "NO2",
    "Tolga": "NO1",
    "Tromsø": "NO4",
    "Trondheim": "NO3",
    "Trysil": "NO1",
    "Træna": "NO4",
    "Tvedestrand": "NO2",
    "Tydal": "NO3",
    "Tynset (nordvest for Nytrøa)": "NO3",
    "Tynset (resten)": "NO1",
    "Tysnes": "NO2",
    "Tysvær": "NO2",
    "Tønsberg": "NO2",
    "Ullensaker": "NO1",
    "Ullensvang (nord)": "NO5",
    "Ullensvang (sør)": "NO2",
    "Ulstein": "NO3",
    "Ulvik": "NO5",
    "Utsira": "NO2",
    "Vadsø": "NO4",
    "Vaksdal": "NO5",
    "Valle": "NO2",
    "Vang": "NO1",
    "Vanylven": "NO3",
    "Vardø": "NO4",
    "Vefsn": "NO4",
    "Vega": "NO4",
    "Vegårshei": "NO2",
    "Vennesla": "NO2",
    "Verdal": "NO3",
    "Vestby": "NO1",
    "Vestnes": "NO3",
    "Vestre Slidre": "NO1",
    "Vestre Toten": "NO1",
    "Vestvågøy": "NO4",
    "Vevelstad": "NO4",
    "Vik": "NO5",
    "Vindafjord": "NO2",
    "Vinje": "NO2",
    "Volda": "NO3",
    "Voss": "NO5",
    "Værøy": "NO4",
    "Vågan": "NO4",
    "Vågå": "NO3",
    "Våler (Innlandet)": "NO1",
    "Våler (Viken)": "NO1",
    "Øksnes": "NO4",
    "Ørland": "NO3",
    "Ørsta": "NO3",
    "Østre Toten": "NO1",
    "Øvre Eiker": "NO1",
    "Øyer": "NO1",
    "Øygarden": "NO5",
    "Øystre Slidre": "NO1",
    "Åfjord": "NO3",
    "Ål": "NO5",
    "Ålesund": "NO3",
    "Åmli": "NO2",
    "Åmot": "NO1",
    "Årdal": "NO5",
    "Ås": "NO1",
    "Åseral": "NO2",
    "Åsnes": "NO1"
  }
